decimal_val2/__init__.py
decimal_val2/core.py
decimal_val2/py.typed
decimal_val2-0.1.0.dist-info/licenses/LICENSE
decimal_val2-0.1.0.dist-info/METADATA
decimal_val2-0.1.0.dist-info/WHEEL
decimal_val2-0.1.0.dist-info/top_level.txt
decimal_val2-0.1.0.dist-info/RECORD
